{
  "id": 12,
  "image": "../images/pepsi1.jpg",
  "title": "Pepsi Light 350ml Can",
  "description": "These features will equip your support team managers with the tools they need to manage customer expectation and agent productivity. These features will equip your support team managers with the tools they need to manage customer expectation and agent productivity.",
  "specs": {
    "manufactured_by": "Sterling Design",
    "made_in": "Germany",
    "style": "Traditional",
    "dimensions": "50 x 50 cm",
    "category": "Flooring"
  },
  "related": [
    {
      "id": 1,
      "image": "../images/pepsi1.jpg",
      "alt": "Image Alt",
      "brand": "Pepsi",
      "gtin": "9238049889",
      "title": "Pepsi Light 350ml Can"
    },
    {
      "id": 2,
      "image": "../images/pepsi2.jpg",
      "alt": "Image Alt",
      "brand": "Pepsi",
      "gtin": "9238049889",
      "title": "Pepsi Light 350ml Can"
    },
    {
      "id": 3,
      "image": "../images/pepsi3.jpg",
      "alt": "Image Alt",
      "brand": "Pepsi",
      "gtin": "9238049889",
      "title": "Pepsi Light 350ml Can"
    },
    {
      "id": 4,
      "image": "../images/pepsi4.jpg",
      "alt": "Image Alt",
      "brand": "Pepsi",
      "gtin": "9238049889",
      "title": "Pepsi Light 350ml Can"
    },
    {
      "id": 5,
      "image": "../images/pepsi5.jpg",
      "alt": "Image Alt",
      "brand": "Pepsi",
      "gtin": "9238049889",
      "title": "Pepsi Light 350ml Can"
    },
    {
      "id": 6,
      "image": "../images/pepsi1.jpg",
      "alt": "Image Alt",
      "brand": "Pepsi",
      "gtin": "9238049889",
      "title": "Pepsi Light 350ml Can"
    }
  ]
}